{
  "NOTICE": "do not edit - this file is autogenerated by `gulp update-metadata`",
  "disclosures": {
    "https://assets.allegrostatic.com/dsp-tcf-external/device-storage.json": {
      "timestamp": "2026-01-21T15:16:33.255Z",
      "disclosures": []
    }
  },
  "components": [
    {
      "componentType": "bidder",
      "componentName": "allegro",
      "aliasOf": null,
      "gvlid": 1493,
      "disclosureURL": "https://assets.allegrostatic.com/dsp-tcf-external/device-storage.json"
    }
  ]
}