{
  "NOTICE": "do not edit - this file is autogenerated by `gulp update-metadata`",
  "disclosures": {},
  "components": [
    {
      "componentType": "bidder",
      "componentName": "aso",
      "aliasOf": null,
      "gvlid": null,
      "disclosureURL": null
    },
    {
      "componentType": "bidder",
      "componentName": "bcmint",
      "aliasOf": "aso",
      "gvlid": null,
      "disclosureURL": null
    },
    {
      "componentType": "bidder",
      "componentName": "bidgency",
      "aliasOf": "aso",
      "gvlid": null,
      "disclosureURL": null
    },
    {
      "componentType": "bidder",
      "componentName": "kuantyx",
      "aliasOf": "aso",
      "gvlid": null,
      "disclosureURL": null
    },
    {
      "componentType": "bidder",
      "componentName": "cordless",
      "aliasOf": "aso",
      "gvlid": null,
      "disclosureURL": null
    }
  ]
}