{
  "NOTICE": "do not edit - this file is autogenerated by `gulp update-metadata`",
  "disclosures": {
    "https://digitalmatter.ai/disclosures.json": {
      "timestamp": "2026-01-21T15:16:40.716Z",
      "disclosures": []
    }
  },
  "components": [
    {
      "componentType": "bidder",
      "componentName": "digitalMatter",
      "aliasOf": null,
      "gvlid": 1345,
      "disclosureURL": "https://digitalmatter.ai/disclosures.json"
    },
    {
      "componentType": "bidder",
      "componentName": "dichange",
      "aliasOf": "digitalMatter",
      "gvlid": null,
      "disclosureURL": null
    },
    {
      "componentType": "bidder",
      "componentName": "digitalmatter",
      "aliasOf": "digitalMatter",
      "gvlid": null,
      "disclosureURL": null
    }
  ]
}