{
  "NOTICE": "do not edit - this file is autogenerated by `gulp update-metadata`",
  "disclosures": {
    "https://onetag-cdn.com/privacy/tcf_storage.json": {
      "timestamp": "2026-06-15T17:39:49.303Z",
      "disclosures": [
        {
          "identifier": "onetag_sid",
          "type": "web",
          "purposes": [
            1,
            2,
            3,
            4,
            7,
            9,
            10
          ]
        }
      ]
    }
  },
  "purposes": {
    "241": {
      "purposes": [
        1,
        2,
        3,
        4,
        7,
        9,
        10
      ],
      "legIntPurposes": [],
      "flexiblePurposes": [
        2,
        7
      ],
      "specialFeatures": [
        1
      ]
    }
  },
  "components": [
    {
      "componentType": "bidder",
      "componentName": "onetag",
      "aliasOf": null,
      "gvlid": 241,
      "disclosureURL": "https://onetag-cdn.com/privacy/tcf_storage.json"
    }
  ]
}