{
  "NOTICE": "do not edit - this file is autogenerated by `gulp update-metadata`",
  "disclosures": {
    "https://bh.contextweb.com/tcf/vendorInfo.json": {
      "timestamp": "2026-01-28T16:30:31.577Z",
      "disclosures": []
    }
  },
  "components": [
    {
      "componentType": "bidder",
      "componentName": "pulsepoint",
      "aliasOf": null,
      "gvlid": 81,
      "disclosureURL": "https://bh.contextweb.com/tcf/vendorInfo.json"
    },
    {
      "componentType": "bidder",
      "componentName": "pulseLite",
      "aliasOf": "pulsepoint",
      "gvlid": null,
      "disclosureURL": null
    },
    {
      "componentType": "bidder",
      "componentName": "pulsepointLite",
      "aliasOf": "pulsepoint",
      "gvlid": null,
      "disclosureURL": null
    }
  ]
}