{
  "NOTICE": "do not edit - this file is autogenerated by `gulp update-metadata`",
  "disclosures": {
    "https://tappx.com/devicestorage.json": {
      "timestamp": "2026-06-01T16:51:29.253Z",
      "disclosures": []
    }
  },
  "purposes": {
    "628": {
      "purposes": [
        1,
        2,
        3,
        4,
        7,
        10
      ],
      "legIntPurposes": [],
      "flexiblePurposes": []
    }
  },
  "components": [
    {
      "componentType": "bidder",
      "componentName": "tappx",
      "aliasOf": null,
      "gvlid": 628,
      "disclosureURL": "https://tappx.com/devicestorage.json"
    }
  ]
}